z3c.bcrypt-2.0.0-py2.7-nspkg.pth
z3c/bcrypt/USAGE.rst
z3c/bcrypt/__init__.py
z3c/bcrypt/configure.zcml
z3c/bcrypt/passwordmanager.py
z3c/bcrypt/tests.py
z3c.bcrypt-2.0.0.dist-info/DESCRIPTION.rst
z3c.bcrypt-2.0.0.dist-info/METADATA
z3c.bcrypt-2.0.0.dist-info/RECORD
z3c.bcrypt-2.0.0.dist-info/WHEEL
z3c.bcrypt-2.0.0.dist-info/entry_points.txt
z3c.bcrypt-2.0.0.dist-info/metadata.json
z3c.bcrypt-2.0.0.dist-info/namespace_packages.txt
z3c.bcrypt-2.0.0.dist-info/top_level.txt
