Metadata-Version: 2.0
Name: z3c.bcrypt
Version: 2.0.0
Summary: Password manager utility using bcrypt or pbkdf2 encoding. Useful in combination with zope.password
Home-page: http://github.com/zopefoundation/z3c.bcrypt
Author: The Health Agency and the Zope Community
Author-email: zope3-dev@zope.org
License: ZPL 2.1
Keywords: zope authentication password bcrypy pbkdf2
Platform: UNKNOWN
Classifier: Development Status :: 5 - Production/Stable
Classifier: Environment :: Web Environment
Classifier: Intended Audience :: Developers
Classifier: License :: OSI Approved :: Zope Public License
Classifier: Programming Language :: Python
Classifier: Natural Language :: English
Classifier: Operating System :: OS Independent
Classifier: Topic :: Internet :: WWW/HTTP
Classifier: Framework :: Zope3
Classifier: Programming Language :: Python
Classifier: Programming Language :: Python :: 2
Classifier: Programming Language :: Python :: 2.7
Classifier: Programming Language :: Python :: 3
Classifier: Programming Language :: Python :: 3.4
Classifier: Programming Language :: Python :: 3.5
Classifier: Programming Language :: Python :: 3.6
Classifier: Programming Language :: Python :: Implementation :: CPython
Classifier: Programming Language :: Python :: Implementation :: PyPy
Requires-Dist: cryptacular
Requires-Dist: setuptools
Requires-Dist: zope.interface
Requires-Dist: zope.password
Provides-Extra: test
Requires-Dist: zope.security; extra == 'test'
Requires-Dist: zope.testing; extra == 'test'
